{
  "port": 5060,
  "clampPromptToContextWindow": true,
  "stream": true,
  "customWorkflowOverride": false,
  "customWorkflow": "",
  "routingConfig": "",
  "categorizationWorkflow": "",
  "defaultParallelProcessWorkflow": "",
  "fileMemoryToolWorkflow": "",
  "chatSummaryToolWorkflow": "",
  "conversationMemoryToolWorkflow": "",
  "recentMemoryToolWorkflow": "",
  "discussionIdMemoryFileWorkflowSettings": "",
  "discussionDirectory": "",
  "sqlLiteDirectory": "",
  "chatPromptTemplateName": "_chatonly",
  "verboseLogging": true,
  "chatCompleteAddUserAssistant": true,
  "chatCompletionAddMissingAssistantGenerator": false,
  "endpointConfigsSubDirectory": "_shared",
  "presetConfigsSubDirectoryOverride": "_shared",
  "allowSharedWorkflows": true,
  "sharedWorkflowsSubDirectoryOverride": "_shared"
}